asian_mtl/__init__.py
asian_mtl/evaluation/__init__.py
asian_mtl/evaluation/cli.py
asian_mtl/evaluation/debug_memory.py
asian_mtl/evaluation/evaluation_pipeline.py
asian_mtl/models/README.md
asian_mtl/models/__init__.py
asian_mtl/models/base.py
asian_mtl-0.1.2.dist-info/LICENSE
asian_mtl-0.1.2.dist-info/WHEEL
asian_mtl-0.1.2.dist-info/METADATA
asian_mtl-0.1.2.dist-info/RECORD
